<?xml version="1.0" encoding="UTF-8"?>

<rdf:RDF
 xmlns:rdf="http://www.w3.org/1999/02/22-rdf-syntax-ns#"
 xmlns="http://purl.org/rss/1.0/"
 xmlns:content="http://purl.org/rss/1.0/modules/content/"
 xmlns:taxo="http://purl.org/rss/1.0/modules/taxonomy/"
 xmlns:dc="http://purl.org/dc/elements/1.1/"
 xmlns:syn="http://purl.org/rss/1.0/modules/syndication/"
 xmlns:admin="http://webns.net/mvcb/"
>

<channel rdf:about="http://del.icio.us/svbsya">
<title>del.icio.us/svbsya</title>
<link>http://del.icio.us/svbsya</link>
<description></description>
<items>
 <rdf:Seq>
  <rdf:li rdf:resource="http://www.badeziner.com/2008/05/04/120-free-ajax-activity-indicator-gif-icons/" />
  <rdf:li rdf:resource="http://www.rootkit.com/index.php" />
  <rdf:li rdf:resource="http://lifehacker.com/380702/five-best-dvd-ripping-tools" />
  <rdf:li rdf:resource="http://www.livecdlist.com/" />
  <rdf:li rdf:resource="http://naqernet.iblogr.com/2006/12/22/come-sbloccare-le-porte-protette-in-firefox/" />
  <rdf:li rdf:resource="http://www.biosflash.com/e/bios-boot-cd2.htm" />
  <rdf:li rdf:resource="http://www.hwmania.org/forum/motherboard-e-chipset/991-guida-creazione-di-un-cd-di-avvio-dos-per-flash-del-bios.html" />
  <rdf:li rdf:resource="http://www.idealista.it/pagina/portada" />
  <rdf:li rdf:resource="http://www.tofslie.com/hey/page/5/" />
  <rdf:li rdf:resource="http://www.tofslie.com/hey/page/3/" />
  <rdf:li rdf:resource="http://www.data-sheet.net/" />
  <rdf:li rdf:resource="http://www.makeuseof.com/tag/5-packs-to-transform-windows-to-other-os/" />
  <rdf:li rdf:resource="http://www.makeuseof.com/tag/5-tools-to-make-windows-xp-look-like-vista/" />
  <rdf:li rdf:resource="http://www.urlpass.com/" />
  <rdf:li rdf:resource="http://www.acronymfinder.com/" />
  <rdf:li rdf:resource="http://www.snapfiles.com/screenshots/yamipod.htm" />
  <rdf:li rdf:resource="http://www.dottorperuginibilli.it/index.php?option=com_content&#x26;task=view&#x26;id=68&#x26;Itemid=129" />
  <rdf:li rdf:resource="http://www.dottorperuginibilli.it/index.php?option=com_content&#x26;task=view&#x26;id=211&#x26;Itemid=141" />
  <rdf:li rdf:resource="http://winpooch.free.fr/page/home.php?lang=en&#x26;page=home" />
  <rdf:li rdf:resource="http://silenceisdefeat.org/" />
  <rdf:li rdf:resource="http://www.floola.com/modules/wiwimod/index.php?page=WiwiHome" />
  <rdf:li rdf:resource="http://www.dissacration.com/2008/06/28/eolo-car/" />
  <rdf:li rdf:resource="http://climate.jpl.nasa.gov/ClimateTimeMachine/climateTimeMachine.cfm" />
  <rdf:li rdf:resource="http://www.c6software.com/Products/PopBox/Default.aspx" />
  <rdf:li rdf:resource="http://www.youtubecatcher.com/" />
  <rdf:li rdf:resource="http://tubeleecher.com/" />
  <rdf:li rdf:resource="http://www.makeuseof.com/tag/4-quick-ways-to-download-youtube-videos-off-the-net/" />
  <rdf:li rdf:resource="http://www.humyo.com/pages/en/online-file-storage" />
  <rdf:li rdf:resource="http://www.makeuseof.com/tag/the-best-free-alternatives-to-nero-cddvd-burner/" />
  <rdf:li rdf:resource="http://www.lamiatariffa.it/pagine/areaclienti/sms-gratis/sms-gratis.php" />
  <rdf:li rdf:resource="http://whytheluckystiff.net/ruby/pickaxe/" />
 </rdf:Seq>
</items>
</channel>

<item rdf:about="http://www.badeziner.com/2008/05/04/120-free-ajax-activity-indicator-gif-icons/">
<title>120+ Free Ajax Activity Indicator Gif Icons | badeziner</title>
<link>http://www.badeziner.com/2008/05/04/120-free-ajax-activity-indicator-gif-icons/</link>
<description></description>
<dc:creator>svbsya</dc:creator>
<dc:date>2008-07-06T09:54:38Z</dc:date>
<dc:subject>activity ajax animation generator icons indicators loading webdesign</dc:subject>
<taxo:topics>
  <rdf:Bag>
    <rdf:li resource="http://del.icio.us/tag/ajax" />
    <rdf:li resource="http://del.icio.us/tag/activity" />
    <rdf:li resource="http://del.icio.us/tag/indicators" />
    <rdf:li resource="http://del.icio.us/tag/icons" />
    <rdf:li resource="http://del.icio.us/tag/loading" />
    <rdf:li resource="http://del.icio.us/tag/animation" />
    <rdf:li resource="http://del.icio.us/tag/webdesign" />
    <rdf:li resource="http://del.icio.us/tag/generator" />
  </rdf:Bag>
</taxo:topics>
</item>

<item rdf:about="http://www.rootkit.com/index.php">
<title>rootkit.com</title>
<link>http://www.rootkit.com/index.php</link>
<description></description>
<dc:creator>svbsya</dc:creator>
<dc:date>2008-07-06T09:52:29Z</dc:date>
<dc:subject>antivirus hacking reference rootkit security tools</dc:subject>
<taxo:topics>
  <rdf:Bag>
    <rdf:li resource="http://del.icio.us/tag/antivirus" />
    <rdf:li resource="http://del.icio.us/tag/security" />
    <rdf:li resource="http://del.icio.us/tag/rootkit" />
    <rdf:li resource="http://del.icio.us/tag/hacking" />
    <rdf:li resource="http://del.icio.us/tag/tools" />
    <rdf:li resource="http://del.icio.us/tag/reference" />
  </rdf:Bag>
</taxo:topics>
</item>

<item rdf:about="http://lifehacker.com/380702/five-best-dvd-ripping-tools">
<title>Hive Five: Five Best DVD Ripping Tools</title>
<link>http://lifehacker.com/380702/five-best-dvd-ripping-tools</link>
<description></description>
<dc:creator>svbsya</dc:creator>
<dc:date>2008-07-03T08:24:28Z</dc:date>
<dc:subject>dvd list rip ripping software tools</dc:subject>
<taxo:topics>
  <rdf:Bag>
    <rdf:li resource="http://del.icio.us/tag/dvd" />
    <rdf:li resource="http://del.icio.us/tag/ripping" />
    <rdf:li resource="http://del.icio.us/tag/software" />
    <rdf:li resource="http://del.icio.us/tag/tools" />
    <rdf:li resource="http://del.icio.us/tag/list" />
    <rdf:li resource="http://del.icio.us/tag/rip" />
  </rdf:Bag>
</taxo:topics>
</item>

<item rdf:about="http://www.livecdlist.com/">
<title>The LiveCD List</title>
<link>http://www.livecdlist.com/</link>
<description></description>
<dc:creator>svbsya</dc:creator>
<dc:date>2008-07-03T07:37:11Z</dc:date>
<dc:subject>linux list live livecd</dc:subject>
<taxo:topics>
  <rdf:Bag>
    <rdf:li resource="http://del.icio.us/tag/linux" />
    <rdf:li resource="http://del.icio.us/tag/livecd" />
    <rdf:li resource="http://del.icio.us/tag/live" />
    <rdf:li resource="http://del.icio.us/tag/list" />
  </rdf:Bag>
</taxo:topics>
</item>

<item rdf:about="http://naqernet.iblogr.com/2006/12/22/come-sbloccare-le-porte-protette-in-firefox/">
<title>Come sbloccare le porte protette in Firefox &#xAB; Naqernet</title>
<link>http://naqernet.iblogr.com/2006/12/22/come-sbloccare-le-porte-protette-in-firefox/</link>
<description>network.security.ports.banned.override</description>
<dc:creator>svbsya</dc:creator>
<dc:date>2008-07-02T16:01:54Z</dc:date>
<dc:subject>blocco block blocked firefox porte ports</dc:subject>
<taxo:topics>
  <rdf:Bag>
    <rdf:li resource="http://del.icio.us/tag/firefox" />
    <rdf:li resource="http://del.icio.us/tag/porte" />
    <rdf:li resource="http://del.icio.us/tag/ports" />
    <rdf:li resource="http://del.icio.us/tag/blocked" />
    <rdf:li resource="http://del.icio.us/tag/block" />
    <rdf:li resource="http://del.icio.us/tag/blocco" />
  </rdf:Bag>
</taxo:topics>
</item>

<item rdf:about="http://www.biosflash.com/e/bios-boot-cd2.htm">
<title>BIOS Update per bootable CD</title>
<link>http://www.biosflash.com/e/bios-boot-cd2.htm</link>
<description></description>
<dc:creator>svbsya</dc:creator>
<dc:date>2008-07-02T14:57:57Z</dc:date>
<dc:subject>bios boot dos flash</dc:subject>
<taxo:topics>
  <rdf:Bag>
    <rdf:li resource="http://del.icio.us/tag/bios" />
    <rdf:li resource="http://del.icio.us/tag/flash" />
    <rdf:li resource="http://del.icio.us/tag/dos" />
    <rdf:li resource="http://del.icio.us/tag/boot" />
  </rdf:Bag>
</taxo:topics>
</item>

<item rdf:about="http://www.hwmania.org/forum/motherboard-e-chipset/991-guida-creazione-di-un-cd-di-avvio-dos-per-flash-del-bios.html">
<title>reazione di un CD di avvio Dos per Flash del bios - HwMania</title>
<link>http://www.hwmania.org/forum/motherboard-e-chipset/991-guida-creazione-di-un-cd-di-avvio-dos-per-flash-del-bios.html</link>
<description></description>
<dc:creator>svbsya</dc:creator>
<dc:date>2008-07-02T14:55:17Z</dc:date>
<dc:subject>bios boot cd dos flash</dc:subject>
<taxo:topics>
  <rdf:Bag>
    <rdf:li resource="http://del.icio.us/tag/flash" />
    <rdf:li resource="http://del.icio.us/tag/dos" />
    <rdf:li resource="http://del.icio.us/tag/cd" />
    <rdf:li resource="http://del.icio.us/tag/boot" />
    <rdf:li resource="http://del.icio.us/tag/bios" />
  </rdf:Bag>
</taxo:topics>
</item>

<item rdf:about="http://www.idealista.it/pagina/portada">
<title>idealista.it - annunci immobiliari di case in vendita e case in affitto</title>
<link>http://www.idealista.it/pagina/portada</link>
<description></description>
<dc:creator>svbsya</dc:creator>
<dc:date>2008-07-02T12:50:35Z</dc:date>
<dc:subject>annunci casa case immobiliari</dc:subject>
<taxo:topics>
  <rdf:Bag>
    <rdf:li resource="http://del.icio.us/tag/casa" />
    <rdf:li resource="http://del.icio.us/tag/case" />
    <rdf:li resource="http://del.icio.us/tag/annunci" />
    <rdf:li resource="http://del.icio.us/tag/immobiliari" />
  </rdf:Bag>
</taxo:topics>
</item>

<item rdf:about="http://www.tofslie.com/hey/page/5/">
<title>hey | by tofslie</title>
<link>http://www.tofslie.com/hey/page/5/</link>
<description></description>
<dc:creator>svbsya</dc:creator>
<dc:date>2008-07-02T07:54:45Z</dc:date>
<dc:subject></dc:subject>
</item>

<item rdf:about="http://www.tofslie.com/hey/page/3/">
<title>hey | by tofslie</title>
<link>http://www.tofslie.com/hey/page/3/</link>
<description></description>
<dc:creator>svbsya</dc:creator>
<dc:date>2008-07-02T07:52:17Z</dc:date>
<dc:subject>mars water</dc:subject>
<taxo:topics>
  <rdf:Bag>
    <rdf:li resource="http://del.icio.us/tag/mars" />
    <rdf:li resource="http://del.icio.us/tag/water" />
  </rdf:Bag>
</taxo:topics>
</item>

<item rdf:about="http://www.data-sheet.net/">
<title>Data Sheet Pdf Search Engine</title>
<link>http://www.data-sheet.net/</link>
<description></description>
<dc:creator>svbsya</dc:creator>
<dc:date>2008-07-01T10:57:07Z</dc:date>
<dc:subject>data document documentation ebook ebooks free online pdf search searchengine</dc:subject>
<taxo:topics>
  <rdf:Bag>
    <rdf:li resource="http://del.icio.us/tag/pdf" />
    <rdf:li resource="http://del.icio.us/tag/search" />
    <rdf:li resource="http://del.icio.us/tag/searchengine" />
    <rdf:li resource="http://del.icio.us/tag/online" />
    <rdf:li resource="http://del.icio.us/tag/free" />
    <rdf:li resource="http://del.icio.us/tag/ebooks" />
    <rdf:li resource="http://del.icio.us/tag/document" />
    <rdf:li resource="http://del.icio.us/tag/ebook" />
    <rdf:li resource="http://del.icio.us/tag/data" />
    <rdf:li resource="http://del.icio.us/tag/documentation" />
  </rdf:Bag>
</taxo:topics>
</item>

<item rdf:about="http://www.makeuseof.com/tag/5-packs-to-transform-windows-to-other-os/">
<title>5 Packs to Transform Windows to other OS | MakeUseOf.com</title>
<link>http://www.makeuseof.com/tag/5-packs-to-transform-windows-to-other-os/</link>
<description></description>
<dc:creator>svbsya</dc:creator>
<dc:date>2008-07-01T08:31:45Z</dc:date>
<dc:subject>linux mac theme themes vista windows xp</dc:subject>
<taxo:topics>
  <rdf:Bag>
    <rdf:li resource="http://del.icio.us/tag/windows" />
    <rdf:li resource="http://del.icio.us/tag/linux" />
    <rdf:li resource="http://del.icio.us/tag/mac" />
    <rdf:li resource="http://del.icio.us/tag/vista" />
    <rdf:li resource="http://del.icio.us/tag/xp" />
    <rdf:li resource="http://del.icio.us/tag/theme" />
    <rdf:li resource="http://del.icio.us/tag/themes" />
  </rdf:Bag>
</taxo:topics>
</item>

<item rdf:about="http://www.makeuseof.com/tag/5-tools-to-make-windows-xp-look-like-vista/">
<title>5 Tools to Make Windows XP Look Like Vista | MakeUseOf.com</title>
<link>http://www.makeuseof.com/tag/5-tools-to-make-windows-xp-look-like-vista/</link>
<description></description>
<dc:creator>svbsya</dc:creator>
<dc:date>2008-07-01T08:31:01Z</dc:date>
<dc:subject>look theme themes trasformation vista xp</dc:subject>
<taxo:topics>
  <rdf:Bag>
    <rdf:li resource="http://del.icio.us/tag/xp" />
    <rdf:li resource="http://del.icio.us/tag/vista" />
    <rdf:li resource="http://del.icio.us/tag/look" />
    <rdf:li resource="http://del.icio.us/tag/trasformation" />
    <rdf:li resource="http://del.icio.us/tag/theme" />
    <rdf:li resource="http://del.icio.us/tag/themes" />
  </rdf:Bag>
</taxo:topics>
</item>

<item rdf:about="http://www.urlpass.com/">
<title>Shorten web addresses and pass them on</title>
<link>http://www.urlpass.com/</link>
<description></description>
<dc:creator>svbsya</dc:creator>
<dc:date>2008-07-01T08:22:22Z</dc:date>
<dc:subject>link short tiny url utilities</dc:subject>
<taxo:topics>
  <rdf:Bag>
    <rdf:li resource="http://del.icio.us/tag/url" />
    <rdf:li resource="http://del.icio.us/tag/utilities" />
    <rdf:li resource="http://del.icio.us/tag/link" />
    <rdf:li resource="http://del.icio.us/tag/short" />
    <rdf:li resource="http://del.icio.us/tag/tiny" />
  </rdf:Bag>
</taxo:topics>
</item>

<item rdf:about="http://www.acronymfinder.com/">
<title>Abbreviations and acronyms dictionary: Find definitions for over 4,219,000 abbreviations, acronyms, and initialisms</title>
<link>http://www.acronymfinder.com/</link>
<description></description>
<dc:creator>svbsya</dc:creator>
<dc:date>2008-07-01T07:55:34Z</dc:date>
<dc:subject>abbreviations acronimi acronym acronyms dictionary reference search</dc:subject>
<taxo:topics>
  <rdf:Bag>
    <rdf:li resource="http://del.icio.us/tag/dictionary" />
    <rdf:li resource="http://del.icio.us/tag/acronyms" />
    <rdf:li resource="http://del.icio.us/tag/reference" />
    <rdf:li resource="http://del.icio.us/tag/abbreviations" />
    <rdf:li resource="http://del.icio.us/tag/acronym" />
    <rdf:li resource="http://del.icio.us/tag/search" />
    <rdf:li resource="http://del.icio.us/tag/acronimi" />
  </rdf:Bag>
</taxo:topics>
</item>

<item rdf:about="http://www.snapfiles.com/screenshots/yamipod.htm">
<title>YamiPod screenshot and download at SnapFiles.com</title>
<link>http://www.snapfiles.com/screenshots/yamipod.htm</link>
<description></description>
<dc:creator>svbsya</dc:creator>
<dc:date>2008-07-01T07:32:50Z</dc:date>
<dc:subject>ipod itunes mp3 portable portables</dc:subject>
<taxo:topics>
  <rdf:Bag>
    <rdf:li resource="http://del.icio.us/tag/ipod" />
    <rdf:li resource="http://del.icio.us/tag/mp3" />
    <rdf:li resource="http://del.icio.us/tag/itunes" />
    <rdf:li resource="http://del.icio.us/tag/portable" />
    <rdf:li resource="http://del.icio.us/tag/portables" />
  </rdf:Bag>
</taxo:topics>
</item>

<item rdf:about="http://www.dottorperuginibilli.it/index.php?option=com_content&#x26;task=view&#x26;id=68&#x26;Itemid=129">
<title>Dottor Perugini Billi - Medicina naturale - La bufala del calcio</title>
<link>http://www.dottorperuginibilli.it/index.php?option=com_content&#x26;task=view&#x26;id=68&#x26;Itemid=129</link>
<description></description>
<dc:creator>svbsya</dc:creator>
<dc:date>2008-06-30T12:39:15Z</dc:date>
<dc:subject>calcio magnesio</dc:subject>
<taxo:topics>
  <rdf:Bag>
    <rdf:li resource="http://del.icio.us/tag/magnesio" />
    <rdf:li resource="http://del.icio.us/tag/calcio" />
  </rdf:Bag>
</taxo:topics>
</item>

<item rdf:about="http://www.dottorperuginibilli.it/index.php?option=com_content&#x26;task=view&#x26;id=211&#x26;Itemid=141">
<title>Dottor Perugini Billi - Medicina naturale - Ipertensione essenziale: le cure alternative</title>
<link>http://www.dottorperuginibilli.it/index.php?option=com_content&#x26;task=view&#x26;id=211&#x26;Itemid=141</link>
<description></description>
<dc:creator>svbsya</dc:creator>
<dc:date>2008-06-30T12:35:59Z</dc:date>
<dc:subject>cure health info medicina medicinanaturale naturale</dc:subject>
<taxo:topics>
  <rdf:Bag>
    <rdf:li resource="http://del.icio.us/tag/medicinanaturale" />
    <rdf:li resource="http://del.icio.us/tag/medicina" />
    <rdf:li resource="http://del.icio.us/tag/naturale" />
    <rdf:li resource="http://del.icio.us/tag/cure" />
    <rdf:li resource="http://del.icio.us/tag/info" />
    <rdf:li resource="http://del.icio.us/tag/health" />
  </rdf:Bag>
</taxo:topics>
</item>

<item rdf:about="http://winpooch.free.fr/page/home.php?lang=en&#x26;page=home">
<title>Winpooch : Windows watchdog helps to detect spywares and trojans - opensource - anti spyware and trojan</title>
<link>http://winpooch.free.fr/page/home.php?lang=en&#x26;page=home</link>
<description></description>
<dc:creator>svbsya</dc:creator>
<dc:date>2008-06-30T07:55:03Z</dc:date>
<dc:subject>antivirus applications apps detect freeware monitoring security software spyware</dc:subject>
<taxo:topics>
  <rdf:Bag>
    <rdf:li resource="http://del.icio.us/tag/security" />
    <rdf:li resource="http://del.icio.us/tag/antivirus" />
    <rdf:li resource="http://del.icio.us/tag/software" />
    <rdf:li resource="http://del.icio.us/tag/freeware" />
    <rdf:li resource="http://del.icio.us/tag/monitoring" />
    <rdf:li resource="http://del.icio.us/tag/spyware" />
    <rdf:li resource="http://del.icio.us/tag/applications" />
    <rdf:li resource="http://del.icio.us/tag/apps" />
    <rdf:li resource="http://del.icio.us/tag/detect" />
  </rdf:Bag>
</taxo:topics>
</item>

<item rdf:about="http://silenceisdefeat.org/">
<title>Silence is Defeat Public Access Unix Systems</title>
<link>http://silenceisdefeat.org/</link>
<description>free shell linux/unix</description>
<dc:creator>svbsya</dc:creator>
<dc:date>2008-06-30T07:19:17Z</dc:date>
<dc:subject>free linux shell ssh</dc:subject>
<taxo:topics>
  <rdf:Bag>
    <rdf:li resource="http://del.icio.us/tag/shell" />
    <rdf:li resource="http://del.icio.us/tag/free" />
    <rdf:li resource="http://del.icio.us/tag/linux" />
    <rdf:li resource="http://del.icio.us/tag/ssh" />
  </rdf:Bag>
</taxo:topics>
</item>

<item rdf:about="http://www.floola.com/modules/wiwimod/index.php?page=WiwiHome">
<title>floola.com - Wiwi - Home</title>
<link>http://www.floola.com/modules/wiwimod/index.php?page=WiwiHome</link>
<description>clone di itune x ipod
</description>
<dc:creator>svbsya</dc:creator>
<dc:date>2008-06-30T07:16:32Z</dc:date>
<dc:subject>freeware ipod itunes linux software windows</dc:subject>
<taxo:topics>
  <rdf:Bag>
    <rdf:li resource="http://del.icio.us/tag/ipod" />
    <rdf:li resource="http://del.icio.us/tag/software" />
    <rdf:li resource="http://del.icio.us/tag/freeware" />
    <rdf:li resource="http://del.icio.us/tag/itunes" />
    <rdf:li resource="http://del.icio.us/tag/linux" />
    <rdf:li resource="http://del.icio.us/tag/windows" />
  </rdf:Bag>
</taxo:topics>
</item>

<item rdf:about="http://www.dissacration.com/2008/06/28/eolo-car/">
<title>Eolo car - Dissacration</title>
<link>http://www.dissacration.com/2008/06/28/eolo-car/</link>
<description></description>
<dc:creator>svbsya</dc:creator>
<dc:date>2008-06-30T06:33:45Z</dc:date>
<dc:subject>air aria auto compressa</dc:subject>
<taxo:topics>
  <rdf:Bag>
    <rdf:li resource="http://del.icio.us/tag/auto" />
    <rdf:li resource="http://del.icio.us/tag/aria" />
    <rdf:li resource="http://del.icio.us/tag/compressa" />
    <rdf:li resource="http://del.icio.us/tag/air" />
  </rdf:Bag>
</taxo:topics>
</item>

<item rdf:about="http://climate.jpl.nasa.gov/ClimateTimeMachine/climateTimeMachine.cfm">
<title>climateTimeMachine</title>
<link>http://climate.jpl.nasa.gov/ClimateTimeMachine/climateTimeMachine.cfm</link>
<description></description>
<dc:creator>svbsya</dc:creator>
<dc:date>2008-06-29T21:47:47Z</dc:date>
<dc:subject>climate nasa science visualization weather</dc:subject>
<taxo:topics>
  <rdf:Bag>
    <rdf:li resource="http://del.icio.us/tag/climate" />
    <rdf:li resource="http://del.icio.us/tag/nasa" />
    <rdf:li resource="http://del.icio.us/tag/visualization" />
    <rdf:li resource="http://del.icio.us/tag/weather" />
    <rdf:li resource="http://del.icio.us/tag/science" />
  </rdf:Bag>
</taxo:topics>
</item>

<item rdf:about="http://www.c6software.com/Products/PopBox/Default.aspx">
<title>PopBox! - Javascript Image Magnification</title>
<link>http://www.c6software.com/Products/PopBox/Default.aspx</link>
<description></description>
<dc:creator>svbsya</dc:creator>
<dc:date>2008-06-29T18:22:33Z</dc:date>
<dc:subject>ajax effects effetti foto image images javascript photo photos</dc:subject>
<taxo:topics>
  <rdf:Bag>
    <rdf:li resource="http://del.icio.us/tag/javascript" />
    <rdf:li resource="http://del.icio.us/tag/image" />
    <rdf:li resource="http://del.icio.us/tag/images" />
    <rdf:li resource="http://del.icio.us/tag/photo" />
    <rdf:li resource="http://del.icio.us/tag/effects" />
    <rdf:li resource="http://del.icio.us/tag/foto" />
    <rdf:li resource="http://del.icio.us/tag/effetti" />
    <rdf:li resource="http://del.icio.us/tag/ajax" />
    <rdf:li resource="http://del.icio.us/tag/photos" />
  </rdf:Bag>
</taxo:topics>
</item>

<item rdf:about="http://www.youtubecatcher.com/">
<title>Download YouTube Videos! Download and save YouTube videos to your pc!</title>
<link>http://www.youtubecatcher.com/</link>
<description></description>
<dc:creator>svbsya</dc:creator>
<dc:date>2008-06-29T16:51:01Z</dc:date>
<dc:subject>catcher converter download tools video videos web youtube</dc:subject>
<taxo:topics>
  <rdf:Bag>
    <rdf:li resource="http://del.icio.us/tag/youtube" />
    <rdf:li resource="http://del.icio.us/tag/download" />
    <rdf:li resource="http://del.icio.us/tag/video" />
    <rdf:li resource="http://del.icio.us/tag/tools" />
    <rdf:li resource="http://del.icio.us/tag/converter" />
    <rdf:li resource="http://del.icio.us/tag/videos" />
    <rdf:li resource="http://del.icio.us/tag/catcher" />
    <rdf:li resource="http://del.icio.us/tag/web" />
  </rdf:Bag>
</taxo:topics>
</item>

<item rdf:about="http://tubeleecher.com/">
<title>Download youtube videos directly in your computer</title>
<link>http://tubeleecher.com/</link>
<description></description>
<dc:creator>svbsya</dc:creator>
<dc:date>2008-06-29T16:50:35Z</dc:date>
<dc:subject>download video youtube</dc:subject>
<taxo:topics>
  <rdf:Bag>
    <rdf:li resource="http://del.icio.us/tag/youtube" />
    <rdf:li resource="http://del.icio.us/tag/video" />
    <rdf:li resource="http://del.icio.us/tag/download" />
  </rdf:Bag>
</taxo:topics>
</item>

<item rdf:about="http://www.makeuseof.com/tag/4-quick-ways-to-download-youtube-videos-off-the-net/">
<title>4 Quick Ways To Download YouTube Videos Off The Net | MakeUseOf.com</title>
<link>http://www.makeuseof.com/tag/4-quick-ways-to-download-youtube-videos-off-the-net/</link>
<description></description>
<dc:creator>svbsya</dc:creator>
<dc:date>2008-06-29T15:58:15Z</dc:date>
<dc:subject>download tools video videos youtube</dc:subject>
<taxo:topics>
  <rdf:Bag>
    <rdf:li resource="http://del.icio.us/tag/youtube" />
    <rdf:li resource="http://del.icio.us/tag/download" />
    <rdf:li resource="http://del.icio.us/tag/video" />
    <rdf:li resource="http://del.icio.us/tag/tools" />
    <rdf:li resource="http://del.icio.us/tag/videos" />
  </rdf:Bag>
</taxo:topics>
</item>

<item rdf:about="http://www.humyo.com/pages/en/online-file-storage">
<title>humyo.com - Free Online File Storage &#x26; Backup Space</title>
<link>http://www.humyo.com/pages/en/online-file-storage</link>
<description>30gb space</description>
<dc:creator>svbsya</dc:creator>
<dc:date>2008-06-29T15:47:35Z</dc:date>
<dc:subject>file free hosting online space storage upload</dc:subject>
<taxo:topics>
  <rdf:Bag>
    <rdf:li resource="http://del.icio.us/tag/storage" />
    <rdf:li resource="http://del.icio.us/tag/online" />
    <rdf:li resource="http://del.icio.us/tag/free" />
    <rdf:li resource="http://del.icio.us/tag/hosting" />
    <rdf:li resource="http://del.icio.us/tag/file" />
    <rdf:li resource="http://del.icio.us/tag/upload" />
    <rdf:li resource="http://del.icio.us/tag/space" />
  </rdf:Bag>
</taxo:topics>
</item>

<item rdf:about="http://www.makeuseof.com/tag/the-best-free-alternatives-to-nero-cddvd-burner/">
<title>The Best, Free Alternatives to Nero CD/DVD Burner | MakeUseOf.com</title>
<link>http://www.makeuseof.com/tag/the-best-free-alternatives-to-nero-cddvd-burner/</link>
<description></description>
<dc:creator>svbsya</dc:creator>
<dc:date>2008-06-29T15:10:25Z</dc:date>
<dc:subject>burn burning cd dvd free freeware nero software</dc:subject>
<taxo:topics>
  <rdf:Bag>
    <rdf:li resource="http://del.icio.us/tag/freeware" />
    <rdf:li resource="http://del.icio.us/tag/burning" />
    <rdf:li resource="http://del.icio.us/tag/software" />
    <rdf:li resource="http://del.icio.us/tag/cd" />
    <rdf:li resource="http://del.icio.us/tag/dvd" />
    <rdf:li resource="http://del.icio.us/tag/free" />
    <rdf:li resource="http://del.icio.us/tag/burn" />
    <rdf:li resource="http://del.icio.us/tag/nero" />
  </rdf:Bag>
</taxo:topics>
</item>

<item rdf:about="http://www.lamiatariffa.it/pagine/areaclienti/sms-gratis/sms-gratis.php">
<title>SMS free</title>
<link>http://www.lamiatariffa.it/pagine/areaclienti/sms-gratis/sms-gratis.php</link>
<description>sms free</description>
<dc:creator>svbsya</dc:creator>
<dc:date>2008-06-28T17:28:32Z</dc:date>
<dc:subject>free online sms</dc:subject>
<taxo:topics>
  <rdf:Bag>
    <rdf:li resource="http://del.icio.us/tag/sms" />
    <rdf:li resource="http://del.icio.us/tag/free" />
    <rdf:li resource="http://del.icio.us/tag/online" />
  </rdf:Bag>
</taxo:topics>
</item>

<item rdf:about="http://whytheluckystiff.net/ruby/pickaxe/">
<title>Programming Ruby: The Pragmatic Programmer's Guide</title>
<link>http://whytheluckystiff.net/ruby/pickaxe/</link>
<description></description>
<dc:creator>svbsya</dc:creator>
<dc:date>2008-06-25T13:58:55Z</dc:date>
<dc:subject>book documentation programming reference ruby rubyonrails tutorial</dc:subject>
<taxo:topics>
  <rdf:Bag>
    <rdf:li resource="http://del.icio.us/tag/ruby" />
    <rdf:li resource="http://del.icio.us/tag/programming" />
    <rdf:li resource="http://del.icio.us/tag/reference" />
    <rdf:li resource="http://del.icio.us/tag/book" />
    <rdf:li resource="http://del.icio.us/tag/documentation" />
    <rdf:li resource="http://del.icio.us/tag/tutorial" />
    <rdf:li resource="http://del.icio.us/tag/rubyonrails" />
  </rdf:Bag>
</taxo:topics>
</item>

</rdf:RDF>
