<?xml version="1.0" encoding="UTF-8"?>

<rdf:RDF
 xmlns:rdf="http://www.w3.org/1999/02/22-rdf-syntax-ns#"
 xmlns="http://purl.org/rss/1.0/"
 xmlns:content="http://purl.org/rss/1.0/modules/content/"
 xmlns:taxo="http://purl.org/rss/1.0/modules/taxonomy/"
 xmlns:dc="http://purl.org/dc/elements/1.1/"
 xmlns:syn="http://purl.org/rss/1.0/modules/syndication/"
 xmlns:admin="http://webns.net/mvcb/"
>

<channel rdf:about="http://del.icio.us/s_nexus">
<title>del.icio.us/s_nexus</title>
<link>http://del.icio.us/s_nexus</link>
<description></description>
<items>
 <rdf:Seq>
  <rdf:li rdf:resource="http://lifehacker.com/397786/kid+proof-your-pc-with-steadystate" />
  <rdf:li rdf:resource="http://www.neowin.net/forum/index.php?showtopic=647233&#x26;hl=" />
  <rdf:li rdf:resource="http://www.goldcirclefarms.com/products/o3_eggs_6.html" />
  <rdf:li rdf:resource="http://www.webmonkey.com/tutorial/Get_Started_With_Django" />
  <rdf:li rdf:resource="http://www.bodybuildingfanatic.com/coloradoexperiment.htm" />
  <rdf:li rdf:resource="http://www.fourhourworkweek.com/blog/2007/04/29/from-geek-to-freak-how-i-gained-34-lbs-of-muscle-in-4-weeks/" />
  <rdf:li rdf:resource="http://www.fourhourworkweek.com/blog/2007/04/06/how-to-lose-20-lbs-of-fat-in-30-days-without-doing-any-exercise/" />
  <rdf:li rdf:resource="https://www.godaddy.com/gdshop/holiday/independence2008/playmovie.asp" />
  <rdf:li rdf:resource="http://lifehacker.com/397597/windows-steadystate-creates-a-wreck+proof-space-for-kids-experiments" />
  <rdf:li rdf:resource="http://www.break.com/index/it-guy-vs-dumb-employees.html" />
  <rdf:li rdf:resource="http://www.gamespot.com/pc/rpg/diablo3/news.html?sid=6193137&#x26;tag=topslot;title;3&#x26;om_act=convert&#x26;om_clk=topslot" />
  <rdf:li rdf:resource="http://www.bestbuy.com/site/olspage.jsp?skuId=8771313&#x26;st=8771313&#x26;lp=1&#x26;type=product&#x26;cp=1&#x26;id=1203815723537" />
  <rdf:li rdf:resource="http://na.blackberry.com/eng/ownerslounge/login.jsp?redirect=%2Feng%2Fownerslounge%2Fdownloads%2Fgames.jsp" />
  <rdf:li rdf:resource="http://www.blackberryfreeware.com/2005/07/free-blackberry-games.html" />
  <rdf:li rdf:resource="http://www.anaivanovic.com/index.php?path=start" />
  <rdf:li rdf:resource="http://gizmodo.com/389324/snls-macgruber-defuses-a-bomb-with-a-battery-rubber-band-and-btw-his-son-is-not-gay" />
  <rdf:li rdf:resource="http://my.break.com/content/view.aspx?ContentID=527110" />
  <rdf:li rdf:resource="http://support.microsoft.com/kb/948472" />
  <rdf:li rdf:resource="http://www.zenbe.com/" />
  <rdf:li rdf:resource="http://www.marketwatch.com/news/story/gas-could-fall-2-if/story.aspx?guid=%7B2673C102-68E0-41D9-9C9A-10EE2E723948%7D&#x26;dist=msr_13" />
  <rdf:li rdf:resource="http://ax.phobos.apple.com.edgesuite.net/WebObjects/MZStoreServices.woa/ws/publishIMix?imixid=176573982&#x26;sf=143441" />
  <rdf:li rdf:resource="http://lifehacker.com/396881/turn-your-xbox-360-into-a-streaming-netflix-player" />
  <rdf:li rdf:resource="http://digital-photography-school.com/blog/how-to-avoid-camera-shake/" />
  <rdf:li rdf:resource="http://www.mensworkoutguide.com/interval_training.html" />
  <rdf:li rdf:resource="http://mensworkoutguide.com/supportive_eating.html" />
  <rdf:li rdf:resource="http://www.mensworkoutguide.com/workout/buildmuscleweek1to2.html" />
  <rdf:li rdf:resource="http://www.wegame.com/watch/Girlfriend_Fortress_2/" />
  <rdf:li rdf:resource="http://www.abc-of-fitness.com/leg-stretch/prone-quadriceps-stretch.asp" />
  <rdf:li rdf:resource="http://www.thq-games.com/uk/thqtv/index/1516" />
  <rdf:li rdf:resource="http://sixrevisions.com/web_design/16_sites_web_design_inspiratio/" />
  <rdf:li rdf:resource="http://sixrevisions.com/rapid-development/9-practical-ways-to-enhance-your-web-development-using-the-firefox-web-developer-extension" />
 </rdf:Seq>
</items>
</channel>

<item rdf:about="http://lifehacker.com/397786/kid+proof-your-pc-with-steadystate">
<title>Screenshot Tour: Kid-Proof Your PC with SteadyState</title>
<link>http://lifehacker.com/397786/kid+proof-your-pc-with-steadystate</link>
<description></description>
<dc:creator>s_nexus</dc:creator>
<dc:date>2008-07-06T09:36:51Z</dc:date>
<dc:subject></dc:subject>
</item>

<item rdf:about="http://www.neowin.net/forum/index.php?showtopic=647233&#x26;hl=">
<title>Who's your favorite DJ? - Neowin Forums</title>
<link>http://www.neowin.net/forum/index.php?showtopic=647233&#x26;hl=</link>
<description></description>
<dc:creator>s_nexus</dc:creator>
<dc:date>2008-07-05T09:12:54Z</dc:date>
<dc:subject></dc:subject>
</item>

<item rdf:about="http://www.goldcirclefarms.com/products/o3_eggs_6.html">
<title>Gold Circle Farms - DHA Omega-3 Cage Free Eggs</title>
<link>http://www.goldcirclefarms.com/products/o3_eggs_6.html</link>
<description></description>
<dc:creator>s_nexus</dc:creator>
<dc:date>2008-07-04T22:10:07Z</dc:date>
<dc:subject></dc:subject>
</item>

<item rdf:about="http://www.webmonkey.com/tutorial/Get_Started_With_Django">
<title>Get Started With Django - Webmonkey</title>
<link>http://www.webmonkey.com/tutorial/Get_Started_With_Django</link>
<description></description>
<dc:creator>s_nexus</dc:creator>
<dc:date>2008-07-04T22:09:57Z</dc:date>
<dc:subject></dc:subject>
</item>

<item rdf:about="http://www.bodybuildingfanatic.com/coloradoexperiment.htm">
<title>The Colorado Experiment, Casey Viator's Workout, Arthur Jones Nautilus Bulletin 1 2 3</title>
<link>http://www.bodybuildingfanatic.com/coloradoexperiment.htm</link>
<description></description>
<dc:creator>s_nexus</dc:creator>
<dc:date>2008-07-04T22:09:54Z</dc:date>
<dc:subject></dc:subject>
</item>

<item rdf:about="http://www.fourhourworkweek.com/blog/2007/04/29/from-geek-to-freak-how-i-gained-34-lbs-of-muscle-in-4-weeks/">
<title>From Geek to Freak: How I Gained 34 lbs. of Muscle in 4&#xA0;Weeks - The Blog of Author Tim Ferriss</title>
<link>http://www.fourhourworkweek.com/blog/2007/04/29/from-geek-to-freak-how-i-gained-34-lbs-of-muscle-in-4-weeks/</link>
<description></description>
<dc:creator>s_nexus</dc:creator>
<dc:date>2008-07-04T22:09:50Z</dc:date>
<dc:subject></dc:subject>
</item>

<item rdf:about="http://www.fourhourworkweek.com/blog/2007/04/06/how-to-lose-20-lbs-of-fat-in-30-days-without-doing-any-exercise/">
<title>How to Lose 20 lbs. of Fat in 30 Days&#x2026; Without Doing Any&#xA0;Exercise - The Blog of Author Tim Ferriss</title>
<link>http://www.fourhourworkweek.com/blog/2007/04/06/how-to-lose-20-lbs-of-fat-in-30-days-without-doing-any-exercise/</link>
<description></description>
<dc:creator>s_nexus</dc:creator>
<dc:date>2008-07-04T22:09:47Z</dc:date>
<dc:subject></dc:subject>
</item>

<item rdf:about="https://www.godaddy.com/gdshop/holiday/independence2008/playmovie.asp">
<title>Happy Independence Day!</title>
<link>https://www.godaddy.com/gdshop/holiday/independence2008/playmovie.asp</link>
<description></description>
<dc:creator>s_nexus</dc:creator>
<dc:date>2008-07-04T00:49:19Z</dc:date>
<dc:subject></dc:subject>
</item>

<item rdf:about="http://lifehacker.com/397597/windows-steadystate-creates-a-wreck+proof-space-for-kids-experiments">
<title>Featured Windows Download: Windows SteadyState Creates a Wreck-Proof Space for Kids, Experiments</title>
<link>http://lifehacker.com/397597/windows-steadystate-creates-a-wreck+proof-space-for-kids-experiments</link>
<description></description>
<dc:creator>s_nexus</dc:creator>
<dc:date>2008-07-02T09:32:01Z</dc:date>
<dc:subject></dc:subject>
</item>

<item rdf:about="http://www.break.com/index/it-guy-vs-dumb-employees.html">
<title>IT Guy Vs Dumb Employees&#xA0;Video</title>
<link>http://www.break.com/index/it-guy-vs-dumb-employees.html</link>
<description></description>
<dc:creator>s_nexus</dc:creator>
<dc:date>2008-07-02T09:09:00Z</dc:date>
<dc:subject></dc:subject>
</item>

<item rdf:about="http://www.gamespot.com/pc/rpg/diablo3/news.html?sid=6193137&#x26;tag=topslot;title;3&#x26;om_act=convert&#x26;om_clk=topslot">
<title>Diablo III First Look - PC News at GameSpot</title>
<link>http://www.gamespot.com/pc/rpg/diablo3/news.html?sid=6193137&#x26;tag=topslot;title;3&#x26;om_act=convert&#x26;om_clk=topslot</link>
<description></description>
<dc:creator>s_nexus</dc:creator>
<dc:date>2008-07-02T02:47:52Z</dc:date>
<dc:subject></dc:subject>
</item>

<item rdf:about="http://www.bestbuy.com/site/olspage.jsp?skuId=8771313&#x26;st=8771313&#x26;lp=1&#x26;type=product&#x26;cp=1&#x26;id=1203815723537">
<title>Toshiba - Satellite Laptop with Intel&#xAE; Pentium&#xAE; Dual-Core Processor T2370 - Onyx Blue Metallic - A205-S5825</title>
<link>http://www.bestbuy.com/site/olspage.jsp?skuId=8771313&#x26;st=8771313&#x26;lp=1&#x26;type=product&#x26;cp=1&#x26;id=1203815723537</link>
<description>screen</description>
<dc:creator>s_nexus</dc:creator>
<dc:date>2008-06-28T16:53:32Z</dc:date>
<dc:subject></dc:subject>
</item>

<item rdf:about="http://na.blackberry.com/eng/ownerslounge/login.jsp?redirect=%2Feng%2Fownerslounge%2Fdownloads%2Fgames.jsp">
<title>BlackBerry Owners Lounge - Login</title>
<link>http://na.blackberry.com/eng/ownerslounge/login.jsp?redirect=%2Feng%2Fownerslounge%2Fdownloads%2Fgames.jsp</link>
<description></description>
<dc:creator>s_nexus</dc:creator>
<dc:date>2008-06-28T03:30:36Z</dc:date>
<dc:subject></dc:subject>
</item>

<item rdf:about="http://www.blackberryfreeware.com/2005/07/free-blackberry-games.html">
<title>Blackberry Freeware - Free Software: Free Blackberry Games</title>
<link>http://www.blackberryfreeware.com/2005/07/free-blackberry-games.html</link>
<description></description>
<dc:creator>s_nexus</dc:creator>
<dc:date>2008-06-28T03:30:33Z</dc:date>
<dc:subject></dc:subject>
</item>

<item rdf:about="http://www.anaivanovic.com/index.php?path=start">
<title>The Ana Ivanovic official website - Home</title>
<link>http://www.anaivanovic.com/index.php?path=start</link>
<description></description>
<dc:creator>s_nexus</dc:creator>
<dc:date>2008-06-27T21:41:06Z</dc:date>
<dc:subject></dc:subject>
</item>

<item rdf:about="http://gizmodo.com/389324/snls-macgruber-defuses-a-bomb-with-a-battery-rubber-band-and-btw-his-son-is-not-gay">
<title>TV: SNL's MacGruber Defuses a Bomb With a Battery, Rubber Band and BTW His Son is Not Gay</title>
<link>http://gizmodo.com/389324/snls-macgruber-defuses-a-bomb-with-a-battery-rubber-band-and-btw-his-son-is-not-gay</link>
<description></description>
<dc:creator>s_nexus</dc:creator>
<dc:date>2008-06-27T20:56:45Z</dc:date>
<dc:subject></dc:subject>
</item>

<item rdf:about="http://my.break.com/content/view.aspx?ContentID=527110">
<title>catchphrase blooper video</title>
<link>http://my.break.com/content/view.aspx?ContentID=527110</link>
<description></description>
<dc:creator>s_nexus</dc:creator>
<dc:date>2008-06-27T20:50:43Z</dc:date>
<dc:subject></dc:subject>
</item>

<item rdf:about="http://support.microsoft.com/kb/948472">
<title>How to extend the Windows Server 2008 evaluation period</title>
<link>http://support.microsoft.com/kb/948472</link>
<description>slmgr.vbs &#x2013;rearm</description>
<dc:creator>s_nexus</dc:creator>
<dc:date>2008-06-27T11:44:16Z</dc:date>
<dc:subject></dc:subject>
</item>

<item rdf:about="http://www.zenbe.com/">
<title>Zenbe : Compose Message</title>
<link>http://www.zenbe.com/</link>
<description></description>
<dc:creator>s_nexus</dc:creator>
<dc:date>2008-06-27T01:31:01Z</dc:date>
<dc:subject></dc:subject>
</item>

<item rdf:about="http://www.marketwatch.com/news/story/gas-could-fall-2-if/story.aspx?guid=%7B2673C102-68E0-41D9-9C9A-10EE2E723948%7D&#x26;dist=msr_13">
<title>Gas could fall to $2 if Congress acts, analysts say - MarketWatch</title>
<link>http://www.marketwatch.com/news/story/gas-could-fall-2-if/story.aspx?guid=%7B2673C102-68E0-41D9-9C9A-10EE2E723948%7D&#x26;dist=msr_13</link>
<description></description>
<dc:creator>s_nexus</dc:creator>
<dc:date>2008-06-26T11:05:03Z</dc:date>
<dc:subject></dc:subject>
</item>

<item rdf:about="http://ax.phobos.apple.com.edgesuite.net/WebObjects/MZStoreServices.woa/ws/publishIMix?imixid=176573982&#x26;sf=143441">
<title>iTunes iMix - Here's to GOTH CHICKS!</title>
<link>http://ax.phobos.apple.com.edgesuite.net/WebObjects/MZStoreServices.woa/ws/publishIMix?imixid=176573982&#x26;sf=143441</link>
<description></description>
<dc:creator>s_nexus</dc:creator>
<dc:date>2008-06-24T22:42:02Z</dc:date>
<dc:subject></dc:subject>
</item>

<item rdf:about="http://lifehacker.com/396881/turn-your-xbox-360-into-a-streaming-netflix-player">
<title>Xbox 360: Turn Your Xbox 360 into a Streaming Netflix Player</title>
<link>http://lifehacker.com/396881/turn-your-xbox-360-into-a-streaming-netflix-player</link>
<description></description>
<dc:creator>s_nexus</dc:creator>
<dc:date>2008-06-24T19:17:52Z</dc:date>
<dc:subject></dc:subject>
</item>

<item rdf:about="http://digital-photography-school.com/blog/how-to-avoid-camera-shake/">
<title>How to Reduce Camera Shake - 6 Techniques</title>
<link>http://digital-photography-school.com/blog/how-to-avoid-camera-shake/</link>
<description></description>
<dc:creator>s_nexus</dc:creator>
<dc:date>2008-06-24T13:03:19Z</dc:date>
<dc:subject></dc:subject>
</item>

<item rdf:about="http://www.mensworkoutguide.com/interval_training.html">
<title>WORKOUT ROUTINE - WORKOUT PROGRAM FOR MEN</title>
<link>http://www.mensworkoutguide.com/interval_training.html</link>
<description>FREE EFFECTIVE WORKOUT ROUTINE FOR MEN. DIFFERENT LEVEL OF WORKOUT ROUTINE IS AVAILABLE</description>
<dc:creator>s_nexus</dc:creator>
<dc:date>2008-06-15T14:28:32Z</dc:date>
<dc:subject></dc:subject>
</item>

<item rdf:about="http://mensworkoutguide.com/supportive_eating.html">
<title>WORKOUT ROUTINE - WORKOUT PROGRAM FOR MEN</title>
<link>http://mensworkoutguide.com/supportive_eating.html</link>
<description>FREE EFFECTIVE WORKOUT ROUTINE FOR MEN. DIFFERENT LEVEL OF WORKOUT ROUTINE IS AVAILABLE</description>
<dc:creator>s_nexus</dc:creator>
<dc:date>2008-06-15T14:28:28Z</dc:date>
<dc:subject></dc:subject>
</item>

<item rdf:about="http://www.mensworkoutguide.com/workout/buildmuscleweek1to2.html">
<title>How To Build Muscle in 16 Weeks - Muscle Building Workout</title>
<link>http://www.mensworkoutguide.com/workout/buildmuscleweek1to2.html</link>
<description>How To Build Muscle in 16 weeks or less. Muscle Building Secrets Revealed</description>
<dc:creator>s_nexus</dc:creator>
<dc:date>2008-06-15T14:28:23Z</dc:date>
<dc:subject></dc:subject>
</item>

<item rdf:about="http://www.wegame.com/watch/Girlfriend_Fortress_2/">
<title>Girlfriend Fortress 2 - TF2 video</title>
<link>http://www.wegame.com/watch/Girlfriend_Fortress_2/</link>
<description></description>
<dc:creator>s_nexus</dc:creator>
<dc:date>2008-06-14T23:01:59Z</dc:date>
<dc:subject></dc:subject>
</item>

<item rdf:about="http://www.abc-of-fitness.com/leg-stretch/prone-quadriceps-stretch.asp">
<title>Prone Quadriceps Stretch (Leg Stretches) @ ABC-of-Fitness</title>
<link>http://www.abc-of-fitness.com/leg-stretch/prone-quadriceps-stretch.asp</link>
<description></description>
<dc:creator>s_nexus</dc:creator>
<dc:date>2008-06-14T05:14:57Z</dc:date>
<dc:subject></dc:subject>
</item>

<item rdf:about="http://www.thq-games.com/uk/thqtv/index/1516">
<title>THQ UK - THQ TV - Saints Row 2 - Activities Trailer</title>
<link>http://www.thq-games.com/uk/thqtv/index/1516</link>
<description></description>
<dc:creator>s_nexus</dc:creator>
<dc:date>2008-06-11T19:29:13Z</dc:date>
<dc:subject></dc:subject>
</item>

<item rdf:about="http://sixrevisions.com/web_design/16_sites_web_design_inspiratio/">
<title>Readers&#x2019; Pick: 16 Sites for Web Design Inspiration - Six Revisions</title>
<link>http://sixrevisions.com/web_design/16_sites_web_design_inspiratio/</link>
<description></description>
<dc:creator>s_nexus</dc:creator>
<dc:date>2008-06-11T15:16:47Z</dc:date>
<dc:subject></dc:subject>
</item>

<item rdf:about="http://sixrevisions.com/rapid-development/9-practical-ways-to-enhance-your-web-development-using-the-firefox-web-developer-extension">
<title>9 Practical Ways to Enhance your Web Development Using the Firefox Web Developer Extension - Six Revisions</title>
<link>http://sixrevisions.com/rapid-development/9-practical-ways-to-enhance-your-web-development-using-the-firefox-web-developer-extension</link>
<description></description>
<dc:creator>s_nexus</dc:creator>
<dc:date>2008-06-11T15:16:45Z</dc:date>
<dc:subject></dc:subject>
</item>

</rdf:RDF>
