<?xml version="1.0" encoding="UTF-8"?>

<rdf:RDF
 xmlns:rdf="http://www.w3.org/1999/02/22-rdf-syntax-ns#"
 xmlns="http://purl.org/rss/1.0/"
 xmlns:content="http://purl.org/rss/1.0/modules/content/"
 xmlns:taxo="http://purl.org/rss/1.0/modules/taxonomy/"
 xmlns:dc="http://purl.org/dc/elements/1.1/"
 xmlns:syn="http://purl.org/rss/1.0/modules/syndication/"
 xmlns:admin="http://webns.net/mvcb/"
>

<channel rdf:about="http://del.icio.us/lellis_sjca">
<title>del.icio.us/lellis_sjca</title>
<link>http://del.icio.us/lellis_sjca</link>
<description></description>
<items>
 <rdf:Seq>
  <rdf:li rdf:resource="http://helpme.att.net/results.php?all=0&#x26;category=140" />
  <rdf:li rdf:resource="http://www.dishnetwork.com/downloads/pdf/whats_on_dish/programming_guides/SD_Channel_Lineup.pdf" />
  <rdf:li rdf:resource="https://customersupport.dishnetwork.com/customercare/payperview/prepMovieList.do" />
  <rdf:li rdf:resource="http://www.dishnetwork.com/content/whats_on_dish/sirius/index.shtml" />
  <rdf:li rdf:resource="http://www.movielink.com/store/web/home/home.jsp;jsessionid=0JMHY05UQYJGOCQ2M5TCAOQ?_requestid=2132585" />
  <rdf:li rdf:resource="http://att.homezonedemo.com/" />
  <rdf:li rdf:resource="http://www.2wire.com/?p=385" />
  <rdf:li rdf:resource="http://www.2wire.com/?p=84" />
  <rdf:li rdf:resource="http://www.att.com/gen/general?pid=7910" />
  <rdf:li rdf:resource="http://formatoz.com/" />
  <rdf:li rdf:resource="http://www.ubuntu.com/products/whatisubuntu" />
  <rdf:li rdf:resource="http://en.wikipedia.org/wiki/California_Hydrogen_Highway" />
  <rdf:li rdf:resource="http://hydrogenhighway.ca.gov/" />
  <rdf:li rdf:resource="http://www.nrel.gov/vehiclesandfuels/ngvtf/pdfs/tom_joseph.pdf" />
  <rdf:li rdf:resource="http://www.netinform.net/H2/H2Stations/H2Stations.aspx?Continent=NA&#x26;StationID=-1" />
  <rdf:li rdf:resource="http://feedsifter.com/create.php" />
  <rdf:li rdf:resource="http://www.cpd.ogi.edu/mst/capstone/17Mistakes.htm" />
  <rdf:li rdf:resource="http://www.eleceng.adelaide.edu.au/personal/dabbott/animal.html" />
  <rdf:li rdf:resource="http://www.customreceipt.com/index.php" />
  <rdf:li rdf:resource="http://distrowatch.com/" />
  <rdf:li rdf:resource="http://weather.yahoo.com/forecast/GMXX1093.html" />
  <rdf:li rdf:resource="http://tv.yahoo.com/" />
  <rdf:li rdf:resource="http://homezone.sbc.yahoo.com/tv.html" />
  <rdf:li rdf:resource="http://www.dishnetwork.com/" />
  <rdf:li rdf:resource="http://spamassassin.apache.org/full/3.1.x/doc/Mail_SpamAssassin_Plugin_DomainKeys.html" />
  <rdf:li rdf:resource="http://www.knujon.com/index.html" />
  <rdf:li rdf:resource="http://www.site-by-site.com/exchanges_asia_pacific.htm" />
  <rdf:li rdf:resource="http://search.ebay.com/nuvi-360_W0QQ_trksidZm37QQfromZR40" />
  <rdf:li rdf:resource="http://www.google.com/products/catalog?q=garmin+nuvi+360&#x26;btnG=Search+Products&#x26;show=li&#x26;cid=7350528038028766792" />
  <rdf:li rdf:resource="http://ekb.dbstalk.com/atthz.htm" />
  <rdf:li rdf:resource="http://adminzen.org/" />
 </rdf:Seq>
</items>
</channel>

<item rdf:about="http://helpme.att.net/results.php?all=0&#x26;category=140">
<title>AT&#x26;T Yahoo! Help - Homezone</title>
<link>http://helpme.att.net/results.php?all=0&#x26;category=140</link>
<description></description>
<dc:creator>lellis_sjca</dc:creator>
<dc:date>2008-07-06T12:57:20Z</dc:date>
<dc:subject>homezone tv</dc:subject>
<taxo:topics>
  <rdf:Bag>
    <rdf:li resource="http://del.icio.us/tag/homezone" />
    <rdf:li resource="http://del.icio.us/tag/tv" />
  </rdf:Bag>
</taxo:topics>
</item>

<item rdf:about="http://www.dishnetwork.com/downloads/pdf/whats_on_dish/programming_guides/SD_Channel_Lineup.pdf">
<title>Dish Network Programming Guide</title>
<link>http://www.dishnetwork.com/downloads/pdf/whats_on_dish/programming_guides/SD_Channel_Lineup.pdf</link>
<description></description>
<dc:creator>lellis_sjca</dc:creator>
<dc:date>2008-07-06T12:52:02Z</dc:date>
<dc:subject>homezone tv</dc:subject>
<taxo:topics>
  <rdf:Bag>
    <rdf:li resource="http://del.icio.us/tag/homezone" />
    <rdf:li resource="http://del.icio.us/tag/tv" />
  </rdf:Bag>
</taxo:topics>
</item>

<item rdf:about="https://customersupport.dishnetwork.com/customercare/payperview/prepMovieList.do">
<title>DISH Network - Pay-Per-View</title>
<link>https://customersupport.dishnetwork.com/customercare/payperview/prepMovieList.do</link>
<description></description>
<dc:creator>lellis_sjca</dc:creator>
<dc:date>2008-07-06T12:49:50Z</dc:date>
<dc:subject>homezone tv</dc:subject>
<taxo:topics>
  <rdf:Bag>
    <rdf:li resource="http://del.icio.us/tag/homezone" />
    <rdf:li resource="http://del.icio.us/tag/tv" />
  </rdf:Bag>
</taxo:topics>
</item>

<item rdf:about="http://www.dishnetwork.com/content/whats_on_dish/sirius/index.shtml">
<title>DISH Network -- SIRIUS Music</title>
<link>http://www.dishnetwork.com/content/whats_on_dish/sirius/index.shtml</link>
<description></description>
<dc:creator>lellis_sjca</dc:creator>
<dc:date>2008-07-06T12:46:46Z</dc:date>
<dc:subject>homezone tv</dc:subject>
<taxo:topics>
  <rdf:Bag>
    <rdf:li resource="http://del.icio.us/tag/homezone" />
    <rdf:li resource="http://del.icio.us/tag/tv" />
  </rdf:Bag>
</taxo:topics>
</item>

<item rdf:about="http://www.movielink.com/store/web/home/home.jsp;jsessionid=0JMHY05UQYJGOCQ2M5TCAOQ?_requestid=2132585">
<title>Movielink - Movie downloads for your PC, TV, or laptop</title>
<link>http://www.movielink.com/store/web/home/home.jsp;jsessionid=0JMHY05UQYJGOCQ2M5TCAOQ?_requestid=2132585</link>
<description></description>
<dc:creator>lellis_sjca</dc:creator>
<dc:date>2008-07-06T12:42:51Z</dc:date>
<dc:subject>homezone tv</dc:subject>
<taxo:topics>
  <rdf:Bag>
    <rdf:li resource="http://del.icio.us/tag/homezone" />
    <rdf:li resource="http://del.icio.us/tag/tv" />
  </rdf:Bag>
</taxo:topics>
</item>

<item rdf:about="http://att.homezonedemo.com/">
<title>AT&#x26;T Homezone Demo</title>
<link>http://att.homezonedemo.com/</link>
<description></description>
<dc:creator>lellis_sjca</dc:creator>
<dc:date>2008-07-06T12:42:18Z</dc:date>
<dc:subject>homezone tv</dc:subject>
<taxo:topics>
  <rdf:Bag>
    <rdf:li resource="http://del.icio.us/tag/homezone" />
    <rdf:li resource="http://del.icio.us/tag/tv" />
  </rdf:Bag>
</taxo:topics>
</item>

<item rdf:about="http://www.2wire.com/?p=385">
<title>2Wire.com: Shifter</title>
<link>http://www.2wire.com/?p=385</link>
<description></description>
<dc:creator>lellis_sjca</dc:creator>
<dc:date>2008-07-06T12:40:26Z</dc:date>
<dc:subject>2wire homezone tv</dc:subject>
<taxo:topics>
  <rdf:Bag>
    <rdf:li resource="http://del.icio.us/tag/2wire" />
    <rdf:li resource="http://del.icio.us/tag/homezone" />
    <rdf:li resource="http://del.icio.us/tag/tv" />
  </rdf:Bag>
</taxo:topics>
</item>

<item rdf:about="http://www.2wire.com/?p=84">
<title>2Wire.com: Intelligent Home Servers (MYNE)</title>
<link>http://www.2wire.com/?p=84</link>
<description></description>
<dc:creator>lellis_sjca</dc:creator>
<dc:date>2008-07-06T12:38:47Z</dc:date>
<dc:subject>2wire homezone tv</dc:subject>
<taxo:topics>
  <rdf:Bag>
    <rdf:li resource="http://del.icio.us/tag/2wire" />
    <rdf:li resource="http://del.icio.us/tag/homezone" />
    <rdf:li resource="http://del.icio.us/tag/tv" />
  </rdf:Bag>
</taxo:topics>
</item>

<item rdf:about="http://www.att.com/gen/general?pid=7910">
<title>AT&#x26;T Homezone(SM) - DISH Network Digital Satellite TV with AT&#x26;T High Speed Internet</title>
<link>http://www.att.com/gen/general?pid=7910</link>
<description></description>
<dc:creator>lellis_sjca</dc:creator>
<dc:date>2008-07-06T12:34:25Z</dc:date>
<dc:subject>homezone tv</dc:subject>
<taxo:topics>
  <rdf:Bag>
    <rdf:li resource="http://del.icio.us/tag/tv" />
    <rdf:li resource="http://del.icio.us/tag/homezone" />
  </rdf:Bag>
</taxo:topics>
</item>

<item rdf:about="http://formatoz.com/">
<title>FormatFactory - File format convert tools (http://www.formatoz.com)</title>
<link>http://formatoz.com/</link>
<description></description>
<dc:creator>lellis_sjca</dc:creator>
<dc:date>2008-07-06T12:33:39Z</dc:date>
<dc:subject>convert</dc:subject>
<taxo:topics>
  <rdf:Bag>
    <rdf:li resource="http://del.icio.us/tag/convert" />
  </rdf:Bag>
</taxo:topics>
</item>

<item rdf:about="http://www.ubuntu.com/products/whatisubuntu">
<title>What is Ubuntu?</title>
<link>http://www.ubuntu.com/products/whatisubuntu</link>
<description></description>
<dc:creator>lellis_sjca</dc:creator>
<dc:date>2008-07-06T02:36:51Z</dc:date>
<dc:subject>Linux</dc:subject>
<taxo:topics>
  <rdf:Bag>
    <rdf:li resource="http://del.icio.us/tag/Linux" />
  </rdf:Bag>
</taxo:topics>
</item>

<item rdf:about="http://en.wikipedia.org/wiki/California_Hydrogen_Highway">
<title>California Hydrogen Highway - Wikipedia, the free encyclopedia</title>
<link>http://en.wikipedia.org/wiki/California_Hydrogen_Highway</link>
<description></description>
<dc:creator>lellis_sjca</dc:creator>
<dc:date>2008-07-06T00:29:13Z</dc:date>
<dc:subject>hydrogen</dc:subject>
<taxo:topics>
  <rdf:Bag>
    <rdf:li resource="http://del.icio.us/tag/hydrogen" />
  </rdf:Bag>
</taxo:topics>
</item>

<item rdf:about="http://hydrogenhighway.ca.gov/">
<title>Home Page: California Hydrogen Highway</title>
<link>http://hydrogenhighway.ca.gov/</link>
<description></description>
<dc:creator>lellis_sjca</dc:creator>
<dc:date>2008-07-06T00:28:58Z</dc:date>
<dc:subject>hydrogen</dc:subject>
<taxo:topics>
  <rdf:Bag>
    <rdf:li resource="http://del.icio.us/tag/hydrogen" />
  </rdf:Bag>
</taxo:topics>
</item>

<item rdf:about="http://www.nrel.gov/vehiclesandfuels/ngvtf/pdfs/tom_joseph.pdf">
<title>http://www.nrel.gov/vehiclesandfuels/ngvtf/pdfs/tom_joseph.pdf</title>
<link>http://www.nrel.gov/vehiclesandfuels/ngvtf/pdfs/tom_joseph.pdf</link>
<description></description>
<dc:creator>lellis_sjca</dc:creator>
<dc:date>2008-07-06T00:27:34Z</dc:date>
<dc:subject>Hydrogen</dc:subject>
<taxo:topics>
  <rdf:Bag>
    <rdf:li resource="http://del.icio.us/tag/Hydrogen" />
  </rdf:Bag>
</taxo:topics>
</item>

<item rdf:about="http://www.netinform.net/H2/H2Stations/H2Stations.aspx?Continent=NA&#x26;StationID=-1">
<title>Fuel Stations - Hydrogen and Fuel Cells</title>
<link>http://www.netinform.net/H2/H2Stations/H2Stations.aspx?Continent=NA&#x26;StationID=-1</link>
<description></description>
<dc:creator>lellis_sjca</dc:creator>
<dc:date>2008-07-06T00:23:47Z</dc:date>
<dc:subject>hydrogen</dc:subject>
<taxo:topics>
  <rdf:Bag>
    <rdf:li resource="http://del.icio.us/tag/hydrogen" />
  </rdf:Bag>
</taxo:topics>
</item>

<item rdf:about="http://feedsifter.com/create.php">
<title>Feed Sifter: Get only the good stuff (mt)</title>
<link>http://feedsifter.com/create.php</link>
<description></description>
<dc:creator>lellis_sjca</dc:creator>
<dc:date>2008-07-02T17:58:19Z</dc:date>
<dc:subject>RSStools</dc:subject>
<taxo:topics>
  <rdf:Bag>
    <rdf:li resource="http://del.icio.us/tag/RSStools" />
  </rdf:Bag>
</taxo:topics>
</item>

<item rdf:about="http://www.cpd.ogi.edu/mst/capstone/17Mistakes.htm">
<title>17 Mistakes Start-Ups Make</title>
<link>http://www.cpd.ogi.edu/mst/capstone/17Mistakes.htm</link>
<description></description>
<dc:creator>lellis_sjca</dc:creator>
<dc:date>2008-06-20T08:35:47Z</dc:date>
<dc:subject>startups</dc:subject>
<taxo:topics>
  <rdf:Bag>
    <rdf:li resource="http://del.icio.us/tag/startups" />
  </rdf:Bag>
</taxo:topics>
</item>

<item rdf:about="http://www.eleceng.adelaide.edu.au/personal/dabbott/animal.html">
<title>Derek Abbott's Animal Noise Page</title>
<link>http://www.eleceng.adelaide.edu.au/personal/dabbott/animal.html</link>
<description></description>
<dc:creator>lellis_sjca</dc:creator>
<dc:date>2008-06-20T08:34:46Z</dc:date>
<dc:subject>Animal Sounds</dc:subject>
<taxo:topics>
  <rdf:Bag>
    <rdf:li resource="http://del.icio.us/tag/Sounds" />
    <rdf:li resource="http://del.icio.us/tag/Animal" />
  </rdf:Bag>
</taxo:topics>
</item>

<item rdf:about="http://www.customreceipt.com/index.php">
<title>Custom Receipt Maker</title>
<link>http://www.customreceipt.com/index.php</link>
<description></description>
<dc:creator>lellis_sjca</dc:creator>
<dc:date>2008-06-20T08:31:25Z</dc:date>
<dc:subject>Expenses</dc:subject>
<taxo:topics>
  <rdf:Bag>
    <rdf:li resource="http://del.icio.us/tag/Expenses" />
  </rdf:Bag>
</taxo:topics>
</item>

<item rdf:about="http://distrowatch.com/">
<title>Linux Distribution</title>
<link>http://distrowatch.com/</link>
<description></description>
<dc:creator>lellis_sjca</dc:creator>
<dc:date>2008-06-16T14:12:27Z</dc:date>
<dc:subject>linux</dc:subject>
<taxo:topics>
  <rdf:Bag>
    <rdf:li resource="http://del.icio.us/tag/linux" />
  </rdf:Bag>
</taxo:topics>
</item>

<item rdf:about="http://weather.yahoo.com/forecast/GMXX1093.html">
<title>Gladbeck Weather Forecasts on Yahoo! Weather#text</title>
<link>http://weather.yahoo.com/forecast/GMXX1093.html</link>
<description></description>
<dc:creator>lellis_sjca</dc:creator>
<dc:date>2008-06-16T12:21:39Z</dc:date>
<dc:subject>germany</dc:subject>
<taxo:topics>
  <rdf:Bag>
    <rdf:li resource="http://del.icio.us/tag/germany" />
  </rdf:Bag>
</taxo:topics>
</item>

<item rdf:about="http://tv.yahoo.com/">
<title>Yahoo! TV</title>
<link>http://tv.yahoo.com/</link>
<description></description>
<dc:creator>lellis_sjca</dc:creator>
<dc:date>2008-06-06T20:27:09Z</dc:date>
<dc:subject>homezone tv</dc:subject>
<taxo:topics>
  <rdf:Bag>
    <rdf:li resource="http://del.icio.us/tag/homezone" />
    <rdf:li resource="http://del.icio.us/tag/tv" />
  </rdf:Bag>
</taxo:topics>
</item>

<item rdf:about="http://homezone.sbc.yahoo.com/tv.html">
<title>AT&#x26;T Homezone Yahoo! Remote</title>
<link>http://homezone.sbc.yahoo.com/tv.html</link>
<description></description>
<dc:creator>lellis_sjca</dc:creator>
<dc:date>2008-06-06T20:26:52Z</dc:date>
<dc:subject>homezone tv</dc:subject>
<taxo:topics>
  <rdf:Bag>
    <rdf:li resource="http://del.icio.us/tag/tv" />
    <rdf:li resource="http://del.icio.us/tag/homezone" />
  </rdf:Bag>
</taxo:topics>
</item>

<item rdf:about="http://www.dishnetwork.com/">
<title>DISH Network</title>
<link>http://www.dishnetwork.com/</link>
<description></description>
<dc:creator>lellis_sjca</dc:creator>
<dc:date>2008-06-06T20:26:43Z</dc:date>
<dc:subject>homezone tv</dc:subject>
<taxo:topics>
  <rdf:Bag>
    <rdf:li resource="http://del.icio.us/tag/homezone" />
    <rdf:li resource="http://del.icio.us/tag/tv" />
  </rdf:Bag>
</taxo:topics>
</item>

<item rdf:about="http://spamassassin.apache.org/full/3.1.x/doc/Mail_SpamAssassin_Plugin_DomainKeys.html">
<title>Mail::SpamAssassin::Plugin::DomainKeys - perform DomainKeys verification tests</title>
<link>http://spamassassin.apache.org/full/3.1.x/doc/Mail_SpamAssassin_Plugin_DomainKeys.html</link>
<description></description>
<dc:creator>lellis_sjca</dc:creator>
<dc:date>2008-06-05T15:33:06Z</dc:date>
<dc:subject>diagnostics.authentication.dk</dc:subject>
<taxo:topics>
  <rdf:Bag>
    <rdf:li resource="http://del.icio.us/tag/diagnostics.authentication.dk" />
  </rdf:Bag>
</taxo:topics>
</item>

<item rdf:about="http://www.knujon.com/index.html">
<title>KnujOn</title>
<link>http://www.knujon.com/index.html</link>
<description></description>
<dc:creator>lellis_sjca</dc:creator>
<dc:date>2008-06-03T22:40:48Z</dc:date>
<dc:subject>antiphishing dnsbl registrar</dc:subject>
<taxo:topics>
  <rdf:Bag>
    <rdf:li resource="http://del.icio.us/tag/dnsbl" />
    <rdf:li resource="http://del.icio.us/tag/registrar" />
    <rdf:li resource="http://del.icio.us/tag/antiphishing" />
  </rdf:Bag>
</taxo:topics>
</item>

<item rdf:about="http://www.site-by-site.com/exchanges_asia_pacific.htm">
<title>International Stock Exchanges: Asia / Pacific</title>
<link>http://www.site-by-site.com/exchanges_asia_pacific.htm</link>
<description></description>
<dc:creator>lellis_sjca</dc:creator>
<dc:date>2008-06-02T20:58:55Z</dc:date>
<dc:subject>stock.exchanges</dc:subject>
<taxo:topics>
  <rdf:Bag>
    <rdf:li resource="http://del.icio.us/tag/stock.exchanges" />
  </rdf:Bag>
</taxo:topics>
</item>

<item rdf:about="http://search.ebay.com/nuvi-360_W0QQ_trksidZm37QQfromZR40">
<title>nuvi 360, GPS Devices, Cell Phone PDA Accessories items on eBay.com</title>
<link>http://search.ebay.com/nuvi-360_W0QQ_trksidZm37QQfromZR40</link>
<description></description>
<dc:creator>lellis_sjca</dc:creator>
<dc:date>2008-06-01T14:15:02Z</dc:date>
<dc:subject>gps linda.gift</dc:subject>
<taxo:topics>
  <rdf:Bag>
    <rdf:li resource="http://del.icio.us/tag/linda.gift" />
    <rdf:li resource="http://del.icio.us/tag/gps" />
  </rdf:Bag>
</taxo:topics>
</item>

<item rdf:about="http://www.google.com/products/catalog?q=garmin+nuvi+360&#x26;btnG=Search+Products&#x26;show=li&#x26;cid=7350528038028766792">
<title>Garmin n&#xFC;vi 360 - GPS receiver - automotive</title>
<link>http://www.google.com/products/catalog?q=garmin+nuvi+360&#x26;btnG=Search+Products&#x26;show=li&#x26;cid=7350528038028766792</link>
<description></description>
<dc:creator>lellis_sjca</dc:creator>
<dc:date>2008-06-01T14:13:59Z</dc:date>
<dc:subject>gps linda.gift</dc:subject>
<taxo:topics>
  <rdf:Bag>
    <rdf:li resource="http://del.icio.us/tag/linda.gift" />
    <rdf:li resource="http://del.icio.us/tag/gps" />
  </rdf:Bag>
</taxo:topics>
</item>

<item rdf:about="http://ekb.dbstalk.com/atthz.htm">
<title>AT&#x26;T Homezone 1022 Receiver</title>
<link>http://ekb.dbstalk.com/atthz.htm</link>
<description></description>
<dc:creator>lellis_sjca</dc:creator>
<dc:date>2008-05-31T19:29:11Z</dc:date>
<dc:subject>homezone tv</dc:subject>
<taxo:topics>
  <rdf:Bag>
    <rdf:li resource="http://del.icio.us/tag/homezone" />
    <rdf:li resource="http://del.icio.us/tag/tv" />
  </rdf:Bag>
</taxo:topics>
</item>

<item rdf:about="http://adminzen.org/">
<title>Admin Zen</title>
<link>http://adminzen.org/</link>
<description></description>
<dc:creator>lellis_sjca</dc:creator>
<dc:date>2008-05-30T17:55:08Z</dc:date>
<dc:subject>development</dc:subject>
<taxo:topics>
  <rdf:Bag>
    <rdf:li resource="http://del.icio.us/tag/development" />
  </rdf:Bag>
</taxo:topics>
</item>

</rdf:RDF>
